[
  {
    "contactId": "contact001",
    "user": {
      "id": "user001",
      "name": "Alice",
      "avatar": "https://example.com/avatar/alice.png"
    },
    "nickname": "Alice",
    "phoneNumbers": [
      {
        "type": "mobile",
        "number": "+1234567890"
      }
    ],
    "emailAddresses": [
      {
        "type": "personal",
        "email": "alice@example.com"
      }
    ],
    "tags": ["friend", "work"],
    "customFields": {
      "favoriteColor": "blue",
      "birthday": "1990-01-01"
    },
    "addedAt": "2023-01-01T09:00:00Z",
    "mutualFriendsCount": 3,
    "settings": {
      "muteNotifications": false,
      "favorite": true
    }
  },
  {
    "contactId": "contact002",
    "user": {
      "id": "user002",
      "name": "Bob",
      "avatar": "https://example.com/avatar/bob.png"
    },
    "nickname": "Bob",
    "phoneNumbers": [
      {
        "type": "mobile",
        "number": "+1987654321"
      }
    ],
    "emailAddresses": [
      {
        "type": "work",
        "email": "bob@work.com"
      }
    ],
    "tags": ["friend"],
    "customFields": {
      "hobby": "reading"
    },
    "addedAt": "2023-01-01T09:05:00Z",
    "mutualFriendsCount": 2,
    "settings": {
      "muteNotifications": true,
      "favorite": false
    }
  },
  {
    "contactId": "contact003",
    "user": {
      "id": "user003",
      "name": "Charlie",
      "avatar": "https://example.com/avatar/charlie.png"
    },
    "nickname": "Charlie",
    "phoneNumbers": [
      {
        "type": "work",
        "number": "+1345678901"
      }
    ],
    "emailAddresses": [
      {
        "type": "personal",
        "email": "charlie@example.com"
      }
    ],
    "tags": ["friend", "colleague"],
    "customFields": {
      "workPosition": "Engineer"
    },
    "addedAt": "2023-01-01T09:10:00Z",
    "mutualFriendsCount": 4,
    "settings": {
      "muteNotifications": false,
      "favorite": true
    }
  },
  {
    "contactId": "contact004",
    "user": {
      "id": "user004",
      "name": "David",
      "avatar": "https://example.com/avatar/david.png"
    },
    "nickname": "David",
    "phoneNumbers": [
      {
        "type": "mobile",
        "number": "+1456789012"
      }
    ],
    "emailAddresses": [
      {
        "type": "work",
        "email": "david@work.com"
      }
    ],
    "tags": ["colleague"],
    "customFields": {
      "company": "TechCorp"
    },
    "addedAt": "2023-01-01T09:15:00Z",
    "mutualFriendsCount": 1,
    "settings": {
      "muteNotifications": true,
      "favorite": false
    }
  },
  {
    "contactId": "contact005",
    "user": {
      "id": "user005",
      "name": "Eve",
      "avatar": "https://example.com/avatar/eve.png"
    },
    "nickname": "Eve",
    "phoneNumbers": [
      {
        "type": "home",
        "number": "+1578901234"
      }
    ],
    "emailAddresses": [
      {
        "type": "other",
        "email": "eve@anothermail.com"
      }
    ],
    "tags": ["friend", "family"],
    "customFields": {
      "favoriteFood": "Pizza"
    },
    "addedAt": "2023-01-01T09:20:00Z",
    "mutualFriendsCount": 5,
    "settings": {
      "muteNotifications": false,
      "favorite": true
    }
  }
]
